flashreader/__main__.py
flashreader/memory/_24lc.py
flashreader/memory/_25aa.py
flashreader/memory/_25lc.py
flashreader/memory/m95.py
flashreader/memory/mx25.py
flashreader/memory/spiflash.py
flashreader/memory/w25q.py
flashreader/platform/ft232h.py
flashreader/platform/raspberrypi.py
flashreader-1.1.0.dist-info/LICENSE
flashreader-1.1.0.dist-info/METADATA
flashreader-1.1.0.dist-info/WHEEL
flashreader-1.1.0.dist-info/entry_points.txt
flashreader-1.1.0.dist-info/top_level.txt
flashreader-1.1.0.dist-info/RECORD
