Metadata-Version: 2.1
Name: flashreader
Version: 1.1.0
Summary: Read/write i2c & spi memory chipsets (Flash & EEPROM)
Author-email: o0Zz <--@gmail.com>
License: MIT License
Project-URL: Homepage, https://github.com/o0Zz/flashreader
Keywords: i2c,spi,eeprom,flash,rpi,flashreader
Classifier: License :: OSI Approved :: MIT License
Classifier: Programming Language :: Python
Classifier: Programming Language :: Python :: 3
Requires-Python: >=3.6
License-File: LICENSE
Requires-Dist: requests>=1.0.0
Provides-Extra: dev
Requires-Dist: pip-tools; extra == "dev"
Requires-Dist: pytest; extra == "dev"
